[
    {
        "db_id": "movies_4",
        "table_names_original": [
            "country",
            "department",
            "gender",
            "genre",
            "keyword",
            "language",
            "language_role",
            "movie",
            "movie_genres",
            "movie_languages",
            "person",
            "movie_crew",
            "production_company",
            "production_country",
            "movie_cast",
            "movie_keywords",
            "movie_company"
        ],
        "table_names": [
            "country",
            "department",
            "gender",
            "genre",
            "keyword",
            "language",
            "language_role",
            "movie",
            "movie_genres",
            "movie_languages",
            "person",
            "movie_crew",
            "production_company",
            "production_country",
            "movie_cast",
            "movie_keywords",
            "movie_company"
        ],
        "column_names_original": [
            [
                -1,
                "*"
            ],
            [
                0,
                "country_id"
            ],
            [
                0,
                "country_iso_code"
            ],
            [
                0,
                "country_name"
            ],
            [
                1,
                "department_id"
            ],
            [
                1,
                "department_name"
            ],
            [
                2,
                "gender_id"
            ],
            [
                2,
                "gender"
            ],
            [
                3,
                "genre_id"
            ],
            [
                3,
                "genre_name"
            ],
            [
                4,
                "keyword_id"
            ],
            [
                4,
                "keyword_name"
            ],
            [
                5,
                "language_id"
            ],
            [
                5,
                "language_code"
            ],
            [
                5,
                "language_name"
            ],
            [
                6,
                "role_id"
            ],
            [
                6,
                "language_role"
            ],
            [
                7,
                "movie_id"
            ],
            [
                7,
                "title"
            ],
            [
                7,
                "budget"
            ],
            [
                7,
                "homepage"
            ],
            [
                7,
                "overview"
            ],
            [
                7,
                "popularity"
            ],
            [
                7,
                "release_date"
            ],
            [
                7,
                "revenue"
            ],
            [
                7,
                "runtime"
            ],
            [
                7,
                "movie_status"
            ],
            [
                7,
                "tagline"
            ],
            [
                7,
                "vote_average"
            ],
            [
                7,
                "vote_count"
            ],
            [
                8,
                "movie_id"
            ],
            [
                8,
                "genre_id"
            ],
            [
                9,
                "movie_id"
            ],
            [
                9,
                "language_id"
            ],
            [
                9,
                "language_role_id"
            ],
            [
                10,
                "person_id"
            ],
            [
                10,
                "person_name"
            ],
            [
                11,
                "movie_id"
            ],
            [
                11,
                "person_id"
            ],
            [
                11,
                "department_id"
            ],
            [
                11,
                "job"
            ],
            [
                12,
                "company_id"
            ],
            [
                12,
                "company_name"
            ],
            [
                13,
                "movie_id"
            ],
            [
                13,
                "country_id"
            ],
            [
                14,
                "movie_id"
            ],
            [
                14,
                "person_id"
            ],
            [
                14,
                "character_name"
            ],
            [
                14,
                "gender_id"
            ],
            [
                14,
                "cast_order"
            ],
            [
                15,
                "movie_id"
            ],
            [
                15,
                "keyword_id"
            ],
            [
                16,
                "movie_id"
            ],
            [
                16,
                "company_id"
            ]
        ],
        "column_names": [
            [
                -1,
                "*"
            ],
            [
                0,
                "country id"
            ],
            [
                0,
                "country iso code"
            ],
            [
                0,
                "country name"
            ],
            [
                1,
                "department id"
            ],
            [
                1,
                "department name"
            ],
            [
                2,
                "gender id"
            ],
            [
                2,
                "gender"
            ],
            [
                3,
                "genre id"
            ],
            [
                3,
                "genre_name"
            ],
            [
                4,
                "keyword id"
            ],
            [
                4,
                "keyword name"
            ],
            [
                5,
                "language id"
            ],
            [
                5,
                "language code"
            ],
            [
                5,
                "language name"
            ],
            [
                6,
                "role id"
            ],
            [
                6,
                "language role"
            ],
            [
                7,
                "movie id"
            ],
            [
                7,
                "title"
            ],
            [
                7,
                "budget"
            ],
            [
                7,
                "homepage"
            ],
            [
                7,
                "overview"
            ],
            [
                7,
                "popularity"
            ],
            [
                7,
                "release date"
            ],
            [
                7,
                "revenue"
            ],
            [
                7,
                "runtime"
            ],
            [
                7,
                "movie_status"
            ],
            [
                7,
                "tagline"
            ],
            [
                7,
                "vote average"
            ],
            [
                7,
                "vote count"
            ],
            [
                8,
                "movie id"
            ],
            [
                8,
                "genre id"
            ],
            [
                9,
                "movie id"
            ],
            [
                9,
                "language id"
            ],
            [
                9,
                "language role id"
            ],
            [
                10,
                "person id"
            ],
            [
                10,
                "person name"
            ],
            [
                11,
                "movie id"
            ],
            [
                11,
                "person id"
            ],
            [
                11,
                "department id"
            ],
            [
                11,
                "job"
            ],
            [
                12,
                "company id"
            ],
            [
                12,
                "company name"
            ],
            [
                13,
                "mivie id"
            ],
            [
                13,
                "country id"
            ],
            [
                14,
                "movie id"
            ],
            [
                14,
                "person id"
            ],
            [
                14,
                "character name"
            ],
            [
                14,
                "gender id"
            ],
            [
                14,
                "cast order"
            ],
            [
                15,
                "movie id"
            ],
            [
                15,
                "keyword id"
            ],
            [
                16,
                "movie id"
            ],
            [
                16,
                "company id"
            ]
        ],
        "column_types": [
            "text",
            "integer",
            "text",
            "text",
            "integer",
            "text",
            "integer",
            "text",
            "integer",
            "text",
            "integer",
            "text",
            "integer",
            "text",
            "text",
            "integer",
            "text",
            "integer",
            "text",
            "integer",
            "text",
            "text",
            "real",
            "date",
            "integer",
            "integer",
            "text",
            "text",
            "real",
            "integer",
            "integer",
            "integer",
            "integer",
            "integer",
            "integer",
            "integer",
            "text",
            "integer",
            "integer",
            "integer",
            "text",
            "integer",
            "text",
            "integer",
            "integer",
            "integer",
            "integer",
            "text",
            "integer",
            "integer",
            "integer",
            "integer",
            "integer",
            "integer"
        ],
        "primary_keys": [
            1,
            4,
            6,
            8,
            10,
            12,
            15,
            17,
            35,
            41
        ],
        "foreign_keys": [
            [
                30,
                17
            ],
            [
                31,
                8
            ],
            [
                34,
                15
            ],
            [
                32,
                17
            ],
            [
                33,
                12
            ],
            [
                38,
                35
            ],
            [
                37,
                17
            ],
            [
                39,
                4
            ],
            [
                43,
                17
            ],
            [
                44,
                1
            ],
            [
                46,
                35
            ],
            [
                45,
                17
            ],
            [
                48,
                6
            ]
        ]
    },
    {
        "db_id": "superstore",
        "table_names_original": [
            "people",
            "product",
            "central_superstore",
            "east_superstore",
            "south_superstore",
            "west_superstore"
        ],
        "table_names": [
            "people",
            "product",
            "central_superstore",
            "east_superstore",
            "south_superstore",
            "west_superstore"
        ],
        "column_names_original": [
            [
                -1,
                "*"
            ],
            [
                0,
                "Customer ID"
            ],
            [
                0,
                "Customer Name"
            ],
            [
                0,
                "Segment"
            ],
            [
                0,
                "Country"
            ],
            [
                0,
                "City"
            ],
            [
                0,
                "State"
            ],
            [
                0,
                "Postal Code"
            ],
            [
                0,
                "Region"
            ],
            [
                1,
                "Product ID"
            ],
            [
                1,
                "Product Name"
            ],
            [
                1,
                "Category"
            ],
            [
                1,
                "Sub-Category"
            ],
            [
                1,
                "Region"
            ],
            [
                2,
                "Row ID"
            ],
            [
                2,
                "Order ID"
            ],
            [
                2,
                "Order Date"
            ],
            [
                2,
                "Ship Date"
            ],
            [
                2,
                "Ship Mode"
            ],
            [
                2,
                "Customer ID"
            ],
            [
                2,
                "Region"
            ],
            [
                2,
                "Product ID"
            ],
            [
                2,
                "Sales"
            ],
            [
                2,
                "Quantity"
            ],
            [
                2,
                "Discount"
            ],
            [
                2,
                "Profit"
            ],
            [
                3,
                "Row ID"
            ],
            [
                3,
                "Order ID"
            ],
            [
                3,
                "Order Date"
            ],
            [
                3,
                "Ship Date"
            ],
            [
                3,
                "Ship Mode"
            ],
            [
                3,
                "Customer ID"
            ],
            [
                3,
                "Region"
            ],
            [
                3,
                "Product ID"
            ],
            [
                3,
                "Sales"
            ],
            [
                3,
                "Quantity"
            ],
            [
                3,
                "Discount"
            ],
            [
                3,
                "Profit"
            ],
            [
                4,
                "Row ID"
            ],
            [
                4,
                "Order ID"
            ],
            [
                4,
                "Order Date"
            ],
            [
                4,
                "Ship Date"
            ],
            [
                4,
                "Ship Mode"
            ],
            [
                4,
                "Customer ID"
            ],
            [
                4,
                "Region"
            ],
            [
                4,
                "Product ID"
            ],
            [
                4,
                "Sales"
            ],
            [
                4,
                "Quantity"
            ],
            [
                4,
                "Discount"
            ],
            [
                4,
                "Profit"
            ],
            [
                5,
                "Row ID"
            ],
            [
                5,
                "Order ID"
            ],
            [
                5,
                "Order Date"
            ],
            [
                5,
                "Ship Date"
            ],
            [
                5,
                "Ship Mode"
            ],
            [
                5,
                "Customer ID"
            ],
            [
                5,
                "Region"
            ],
            [
                5,
                "Product ID"
            ],
            [
                5,
                "Sales"
            ],
            [
                5,
                "Quantity"
            ],
            [
                5,
                "Discount"
            ],
            [
                5,
                "Profit"
            ]
        ],
        "column_names": [
            [
                -1,
                "*"
            ],
            [
                0,
                "Customer ID"
            ],
            [
                0,
                "Customer Name"
            ],
            [
                0,
                "Segment"
            ],
            [
                0,
                "Country"
            ],
            [
                0,
                "City"
            ],
            [
                0,
                "State"
            ],
            [
                0,
                "Postal Code"
            ],
            [
                0,
                "Region"
            ],
            [
                1,
                "Product ID"
            ],
            [
                1,
                "Product Name"
            ],
            [
                1,
                "Category"
            ],
            [
                1,
                "Sub-Category"
            ],
            [
                1,
                "Region"
            ],
            [
                2,
                "row id"
            ],
            [
                2,
                "order id"
            ],
            [
                2,
                "order date"
            ],
            [
                2,
                "ship date"
            ],
            [
                2,
                "ship mode"
            ],
            [
                2,
                "customer id"
            ],
            [
                2,
                "Region"
            ],
            [
                2,
                "product id"
            ],
            [
                2,
                "Sales"
            ],
            [
                2,
                "Quantity"
            ],
            [
                2,
                "Discount"
            ],
            [
                2,
                "Profit"
            ],
            [
                3,
                "row id"
            ],
            [
                3,
                "order id"
            ],
            [
                3,
                "order date"
            ],
            [
                3,
                "ship date"
            ],
            [
                3,
                "ship mode"
            ],
            [
                3,
                "customer id"
            ],
            [
                3,
                "Region"
            ],
            [
                3,
                "product id"
            ],
            [
                3,
                "Sales"
            ],
            [
                3,
                "Quantity"
            ],
            [
                3,
                "Discount"
            ],
            [
                3,
                "Profit"
            ],
            [
                4,
                "row id"
            ],
            [
                4,
                "order id"
            ],
            [
                4,
                "order date"
            ],
            [
                4,
                "ship date"
            ],
            [
                4,
                "ship mode"
            ],
            [
                4,
                "customer id"
            ],
            [
                4,
                "Region"
            ],
            [
                4,
                "product id"
            ],
            [
                4,
                "Sales"
            ],
            [
                4,
                "Quantity"
            ],
            [
                4,
                "Discount"
            ],
            [
                4,
                "Profit"
            ],
            [
                5,
                "row id"
            ],
            [
                5,
                "order id"
            ],
            [
                5,
                "order date"
            ],
            [
                5,
                "ship date"
            ],
            [
                5,
                "ship mode"
            ],
            [
                5,
                "customer id"
            ],
            [
                5,
                "Region"
            ],
            [
                5,
                "product id"
            ],
            [
                5,
                "Sales"
            ],
            [
                5,
                "Quantity"
            ],
            [
                5,
                "Discount"
            ],
            [
                5,
                "Profit"
            ]
        ],
        "column_types": [
            "text",
            "text",
            "text",
            "text",
            "text",
            "text",
            "text",
            "integer",
            "text",
            "text",
            "text",
            "text",
            "text",
            "text",
            "integer",
            "text",
            "date",
            "date",
            "text",
            "text",
            "text",
            "text",
            "real",
            "integer",
            "real",
            "real",
            "integer",
            "text",
            "date",
            "date",
            "text",
            "text",
            "text",
            "text",
            "real",
            "integer",
            "real",
            "real",
            "integer",
            "text",
            "date",
            "date",
            "text",
            "text",
            "text",
            "text",
            "real",
            "integer",
            "real",
            "real",
            "integer",
            "text",
            "date",
            "date",
            "text",
            "text",
            "text",
            "text",
            "real",
            "integer",
            "real",
            "real"
        ],
        "primary_keys": [
            [
                1,
                8
            ],
            [
                9,
                13
            ],
            14,
            26,
            38,
            50
        ],
        "foreign_keys": [
            [
                21,
                9
            ],
            [
                20,
                13
            ],
            [
                19,
                1
            ],
            [
                20,
                8
            ],
            [
                33,
                9
            ],
            [
                32,
                13
            ],
            [
                31,
                1
            ],
            [
                32,
                8
            ],
            [
                45,
                9
            ],
            [
                44,
                13
            ],
            [
                43,
                1
            ],
            [
                44,
                8
            ],
            [
                57,
                9
            ],
            [
                56,
                13
            ],
            [
                55,
                1
            ],
            [
                56,
                8
            ]
        ]
    },
    {
        "db_id": "debit_card_specializing",
        "table_names_original": [
            "customers",
            "gasstations",
            "products",
            "transactions_1k",
            "yearmonth"
        ],
        "table_names": [
            "customers",
            "gas stations",
            "products",
            "transactions",
            "year and month"
        ],
        "column_names_original": [
            [
                -1,
                "*"
            ],
            [
                0,
                "CustomerID"
            ],
            [
                0,
                "Segment"
            ],
            [
                0,
                "Currency"
            ],
            [
                1,
                "GasStationID"
            ],
            [
                1,
                "ChainID"
            ],
            [
                1,
                "Country"
            ],
            [
                1,
                "Segment"
            ],
            [
                2,
                "ProductID"
            ],
            [
                2,
                "Description"
            ],
            [
                3,
                "TransactionID"
            ],
            [
                3,
                "Date"
            ],
            [
                3,
                "Time"
            ],
            [
                3,
                "CustomerID"
            ],
            [
                3,
                "CardID"
            ],
            [
                3,
                "GasStationID"
            ],
            [
                3,
                "ProductID"
            ],
            [
                3,
                "Amount"
            ],
            [
                3,
                "Price"
            ],
            [
                4,
                "CustomerID"
            ],
            [
                4,
                "Date"
            ],
            [
                4,
                "Consumption"
            ]
        ],
        "column_names": [
            [
                -1,
                "*"
            ],
            [
                0,
                "CustomerID"
            ],
            [
                0,
                "client segment"
            ],
            [
                0,
                "Currency"
            ],
            [
                1,
                "Gas Station ID"
            ],
            [
                1,
                "Chain ID"
            ],
            [
                1,
                "Country"
            ],
            [
                1,
                "chain segment"
            ],
            [
                2,
                "Product ID"
            ],
            [
                2,
                "Description"
            ],
            [
                3,
                "Transaction ID"
            ],
            [
                3,
                "Date"
            ],
            [
                3,
                "Time"
            ],
            [
                3,
                "Customer ID"
            ],
            [
                3,
                "Card ID"
            ],
            [
                3,
                "Gas Station ID"
            ],
            [
                3,
                "Product ID"
            ],
            [
                3,
                "Amount"
            ],
            [
                3,
                "Price"
            ],
            [
                4,
                "Customer ID"
            ],
            [
                4,
                "Date"
            ],
            [
                4,
                "Consumption"
            ]
        ],
        "column_types": [
            "text",
            "integer",
            "text",
            "text",
            "integer",
            "integer",
            "text",
            "text",
            "integer",
            "text",
            "integer",
            "date",
            "text",
            "integer",
            "integer",
            "integer",
            "integer",
            "integer",
            "real",
            "integer",
            "text",
            "real"
        ],
        "primary_keys": [
            1,
            4,
            8,
            10,
            [
                19,
                20
            ]
        ],
        "foreign_keys": [
            [
                19,
                1
            ]
        ]
    },
    {
        "db_id": "formula_1",
        "table_names_original": [
            "circuits",
            "constructors",
            "drivers",
            "seasons",
            "races",
            "constructorResults",
            "constructorStandings",
            "driverStandings",
            "lapTimes",
            "pitStops",
            "qualifying",
            "status",
            "results"
        ],
        "table_names": [
            "circuits",
            "constructors",
            "drivers",
            "seasons",
            "races",
            "constructor results",
            "constructor standings",
            "driver standings",
            "lap times",
            "pit stops",
            "qualifying",
            "status",
            "results"
        ],
        "column_names_original": [
            [
                -1,
                "*"
            ],
            [
                0,
                "circuitId"
            ],
            [
                0,
                "circuitRef"
            ],
            [
                0,
                "name"
            ],
            [
                0,
                "location"
            ],
            [
                0,
                "country"
            ],
            [
                0,
                "lat"
            ],
            [
                0,
                "lng"
            ],
            [
                0,
                "alt"
            ],
            [
                0,
                "url"
            ],
            [
                1,
                "constructorId"
            ],
            [
                1,
                "constructorRef"
            ],
            [
                1,
                "name"
            ],
            [
                1,
                "nationality"
            ],
            [
                1,
                "url"
            ],
            [
                2,
                "driverId"
            ],
            [
                2,
                "driverRef"
            ],
            [
                2,
                "number"
            ],
            [
                2,
                "code"
            ],
            [
                2,
                "forename"
            ],
            [
                2,
                "surname"
            ],
            [
                2,
                "dob"
            ],
            [
                2,
                "nationality"
            ],
            [
                2,
                "url"
            ],
            [
                3,
                "year"
            ],
            [
                3,
                "url"
            ],
            [
                4,
                "raceId"
            ],
            [
                4,
                "year"
            ],
            [
                4,
                "round"
            ],
            [
                4,
                "circuitId"
            ],
            [
                4,
                "name"
            ],
            [
                4,
                "date"
            ],
            [
                4,
                "time"
            ],
            [
                4,
                "url"
            ],
            [
                5,
                "constructorResultsId"
            ],
            [
                5,
                "raceId"
            ],
            [
                5,
                "constructorId"
            ],
            [
                5,
                "points"
            ],
            [
                5,
                "status"
            ],
            [
                6,
                "constructorStandingsId"
            ],
            [
                6,
                "raceId"
            ],
            [
                6,
                "constructorId"
            ],
            [
                6,
                "points"
            ],
            [
                6,
                "position"
            ],
            [
                6,
                "positionText"
            ],
            [
                6,
                "wins"
            ],
            [
                7,
                "driverStandingsId"
            ],
            [
                7,
                "raceId"
            ],
            [
                7,
                "driverId"
            ],
            [
                7,
                "points"
            ],
            [
                7,
                "position"
            ],
            [
                7,
                "positionText"
            ],
            [
                7,
                "wins"
            ],
            [
                8,
                "raceId"
            ],
            [
                8,
                "driverId"
            ],
            [
                8,
                "lap"
            ],
            [
                8,
                "position"
            ],
            [
                8,
                "time"
            ],
            [
                8,
                "milliseconds"
            ],
            [
                9,
                "raceId"
            ],
            [
                9,
                "driverId"
            ],
            [
                9,
                "stop"
            ],
            [
                9,
                "lap"
            ],
            [
                9,
                "time"
            ],
            [
                9,
                "duration"
            ],
            [
                9,
                "milliseconds"
            ],
            [
                10,
                "qualifyId"
            ],
            [
                10,
                "raceId"
            ],
            [
                10,
                "driverId"
            ],
            [
                10,
                "constructorId"
            ],
            [
                10,
                "number"
            ],
            [
                10,
                "position"
            ],
            [
                10,
                "q1"
            ],
            [
                10,
                "q2"
            ],
            [
                10,
                "q3"
            ],
            [
                11,
                "statusId"
            ],
            [
                11,
                "status"
            ],
            [
                12,
                "resultId"
            ],
            [
                12,
                "raceId"
            ],
            [
                12,
                "driverId"
            ],
            [
                12,
                "constructorId"
            ],
            [
                12,
                "number"
            ],
            [
                12,
                "grid"
            ],
            [
                12,
                "position"
            ],
            [
                12,
                "positionText"
            ],
            [
                12,
                "positionOrder"
            ],
            [
                12,
                "points"
            ],
            [
                12,
                "laps"
            ],
            [
                12,
                "time"
            ],
            [
                12,
                "milliseconds"
            ],
            [
                12,
                "fastestLap"
            ],
            [
                12,
                "rank"
            ],
            [
                12,
                "fastestLapTime"
            ],
            [
                12,
                "fastestLapSpeed"
            ],
            [
                12,
                "statusId"
            ]
        ],
        "column_names": [
            [
                -1,
                "*"
            ],
            [
                0,
                "circuit Id"
            ],
            [
                0,
                "circuit reference name"
            ],
            [
                0,
                "name"
            ],
            [
                0,
                "location"
            ],
            [
                0,
                "country"
            ],
            [
                0,
                "latitude"
            ],
            [
                0,
                "longitude"
            ],
            [
                0,
                "alt"
            ],
            [
                0,
                "url"
            ],
            [
                1,
                "constructor Id"
            ],
            [
                1,
                "Constructor Reference name"
            ],
            [
                1,
                "name"
            ],
            [
                1,
                "nationality"
            ],
            [
                1,
                "url"
            ],
            [
                2,
                "driver ID"
            ],
            [
                2,
                "driver reference name"
            ],
            [
                2,
                "number"
            ],
            [
                2,
                "code"
            ],
            [
                2,
                "forename"
            ],
            [
                2,
                "surname"
            ],
            [
                2,
                "date of birth"
            ],
            [
                2,
                "nationality"
            ],
            [
                2,
                "url"
            ],
            [
                3,
                "race ID"
            ],
            [
                3,
                "url"
            ],
            [
                4,
                "race ID"
            ],
            [
                4,
                "year"
            ],
            [
                4,
                "round"
            ],
            [
                4,
                "Circuit Id"
            ],
            [
                4,
                "name"
            ],
            [
                4,
                "date"
            ],
            [
                4,
                "time"
            ],
            [
                4,
                "url"
            ],
            [
                5,
                "constructor Results Id"
            ],
            [
                5,
                "race Id"
            ],
            [
                5,
                "constructor Id"
            ],
            [
                5,
                "points"
            ],
            [
                5,
                "status"
            ],
            [
                6,
                "constructor Standings Id"
            ],
            [
                6,
                "race id"
            ],
            [
                6,
                "constructor id"
            ],
            [
                6,
                "points"
            ],
            [
                6,
                "position"
            ],
            [
                6,
                "position text"
            ],
            [
                6,
                "wins"
            ],
            [
                7,
                "driver Standings Id"
            ],
            [
                7,
                "constructor Reference name"
            ],
            [
                7,
                "driverId"
            ],
            [
                7,
                "points"
            ],
            [
                7,
                "position"
            ],
            [
                7,
                "position text"
            ],
            [
                7,
                "wins"
            ],
            [
                8,
                "race ID"
            ],
            [
                8,
                "driver ID"
            ],
            [
                8,
                "lap"
            ],
            [
                8,
                "position"
            ],
            [
                8,
                "time"
            ],
            [
                8,
                "milliseconds"
            ],
            [
                9,
                "race ID"
            ],
            [
                9,
                "driver ID"
            ],
            [
                9,
                "stop"
            ],
            [
                9,
                "lap"
            ],
            [
                9,
                "time"
            ],
            [
                9,
                "duration"
            ],
            [
                9,
                "milliseconds"
            ],
            [
                10,
                "qualify Id"
            ],
            [
                10,
                "race Id"
            ],
            [
                10,
                "driver Id"
            ],
            [
                10,
                "constructor id"
            ],
            [
                10,
                "number"
            ],
            [
                10,
                "position"
            ],
            [
                10,
                "qualifying 1"
            ],
            [
                10,
                "qualifying 2"
            ],
            [
                10,
                "qualifying 3"
            ],
            [
                11,
                "status ID"
            ],
            [
                11,
                "status"
            ],
            [
                12,
                "Result ID"
            ],
            [
                12,
                "race ID"
            ],
            [
                12,
                "driver ID"
            ],
            [
                12,
                "constructor Id"
            ],
            [
                12,
                "number"
            ],
            [
                12,
                "grid"
            ],
            [
                12,
                "position"
            ],
            [
                12,
                "position text"
            ],
            [
                12,
                "position order"
            ],
            [
                12,
                "points"
            ],
            [
                12,
                "laps"
            ],
            [
                12,
                "time"
            ],
            [
                12,
                "milliseconds"
            ],
            [
                12,
                "fastest lap"
            ],
            [
                12,
                "rank"
            ],
            [
                12,
                "fastest Lap Time"
            ],
            [
                12,
                "fastest Lap Speed"
            ],
            [
                12,
                "status Id"
            ]
        ],
        "column_types": [
            "text",
            "integer",
            "text",
            "text",
            "text",
            "text",
            "real",
            "real",
            "integer",
            "text",
            "integer",
            "text",
            "text",
            "text",
            "text",
            "integer",
            "text",
            "integer",
            "text",
            "text",
            "text",
            "date",
            "text",
            "text",
            "integer",
            "text",
            "integer",
            "integer",
            "integer",
            "integer",
            "text",
            "date",
            "text",
            "text",
            "integer",
            "integer",
            "integer",
            "real",
            "text",
            "integer",
            "integer",
            "integer",
            "real",
            "integer",
            "text",
            "integer",
            "integer",
            "integer",
            "integer",
            "real",
            "integer",
            "text",
            "integer",
            "integer",
            "integer",
            "integer",
            "integer",
            "text",
            "integer",
            "integer",
            "integer",
            "integer",
            "integer",
            "text",
            "text",
            "integer",
            "integer",
            "integer",
            "integer",
            "integer",
            "integer",
            "integer",
            "text",
            "text",
            "text",
            "integer",
            "text",
            "integer",
            "integer",
            "integer",
            "integer",
            "integer",
            "integer",
            "integer",
            "text",
            "integer",
            "real",
            "integer",
            "text",
            "integer",
            "integer",
            "integer",
            "text",
            "text",
            "integer"
        ],
        "primary_keys": [
            1,
            10,
            15,
            24,
            26,
            34,
            39,
            46,
            [
                53,
                54,
                55
            ],
            [
                59,
                60,
                61
            ],
            66,
            75,
            77
        ],
        "foreign_keys": [
            [
                29,
                1
            ],
            [
                27,
                24
            ],
            [
                36,
                10
            ],
            [
                35,
                26
            ],
            [
                41,
                10
            ],
            [
                40,
                26
            ],
            [
                48,
                15
            ],
            [
                47,
                26
            ],
            [
                54,
                15
            ],
            [
                53,
                26
            ],
            [
                60,
                15
            ],
            [
                59,
                26
            ],
            [
                69,
                10
            ],
            [
                68,
                15
            ],
            [
                67,
                26
            ],
            [
                94,
                75
            ],
            [
                80,
                10
            ],
            [
                79,
                15
            ],
            [
                78,
                26
            ]
        ]
    }
]